{
    "batch_size": 8,
    "val_batch_size": 16,
    "print_log": false,
    "steps": 1e3,
    "checkpoint_steps": 1e1,
    "autoencoder_model": "C:\\Users\\cervaf\\Documents\\Logging\\autoencoder_training\\tested\\best_ver0.5.5_124450.pth",
    "log_dir": "C:\\Users\\cervaf\\Documents\\Logging\\segmentation_training", 
    "data_dir": "C:\\Users\\cervaf\\Documents\\Datasets\\Kidney\\Labeled_examples_comp",
    "dataset": "Histology",
    "workers": 4,
    "channels_org": 3,
    "learning_rate": 1e-4,
    "scheduler": "ReduceOnPlateau",
    "channels_net": 128,
    "channels_bn": 48,
    "compression_level": 3,
    "criterion": "CE",
    "model_type": "DecoderUNet",
    "normalize": false,
    "use_gpu": false,
    "patch_size": 32
}
